README.md
setup.py
brackets_closed/__init__.py
brackets_closed/close_check.py
brackets_closed.egg-info/PKG-INFO
brackets_closed.egg-info/SOURCES.txt
brackets_closed.egg-info/dependency_links.txt
brackets_closed.egg-info/not-zip-safe
brackets_closed.egg-info/top_level.txt