Metadata-Version: 2.1
Name: brackets-closed
Version: 0.9
Summary: Checks if brackets are closed given a string
Home-page: http://pypi.python.org/pypi/brackets_closed/0.9
Author: Daniel Keighley
Author-email: daniel.keighley@wpengine.com
License: WP
Platform: UNKNOWN
